datpy
