Metadata-Version: 1.1
Name: datpy
Version: 0.5.3
Summary: Python dough for making Dat-flavored pies
Home-page: http://dat-data.com
Author: Karissa McKelvey
Author-email: krmckelv@gmail.com
License: UNKNOWN
Download-URL: https://github.com/karissa/datpy/tarball/0.5.3
Keywords: dat,python,analytics,data sharing
Platform: UNKNOWN
